icinga2_exporter/__init__.py
icinga2_exporter/__main__.py
icinga2_exporter/fileconfiguration.py
icinga2_exporter/log.py
icinga2_exporter/main.py
icinga2_exporter/monitorconnection.py
icinga2_exporter/perfdata.py
icinga2_exporter/proxy.py
icinga2_exporter-1.5.1.dist-info/COPYING
icinga2_exporter-1.5.1.dist-info/LICENSE
icinga2_exporter-1.5.1.dist-info/METADATA
icinga2_exporter-1.5.1.dist-info/WHEEL
icinga2_exporter-1.5.1.dist-info/top_level.txt
icinga2_exporter-1.5.1.dist-info/RECORD
