Metadata-Version: 2.1
Name: icinga2-exporter
Version: 1.5.1
Summary: A Prometheus exporter for Icinga2
Home-page: https://github.com/opsdis/icinga2-exporter
Author: thenodon
Author-email: anders@opsdis.com
License: GPLv3
Requires-Python: >=3.6
License-File: LICENSE
License-File: COPYING
Requires-Dist: aiohttp ==3.10.10
Requires-Dist: asyncio ==3.4.3
Requires-Dist: prometheus-client ==0.14.1
Requires-Dist: python-json-logger ==2.0.2
Requires-Dist: PyYAML ==6.0.2
Requires-Dist: quart ==0.17.0
Requires-Dist: requests ==2.31.0
Requires-Dist: werkzeug ==2.3.7
